bs_scheduler/__init__.py
bs_scheduler/batch_size_manager.py
bs_scheduler/batch_size_schedulers.py
bs_scheduler/utils.py
bs_scheduler-1.0.2.dist-info/licenses/LICENSE
bs_scheduler-1.0.2.dist-info/METADATA
bs_scheduler-1.0.2.dist-info/WHEEL
bs_scheduler-1.0.2.dist-info/top_level.txt
bs_scheduler-1.0.2.dist-info/RECORD
