Metadata-Version: 2.4
Name: bs-scheduler
Version: 1.0.2
Summary: A PyTorch Dataloader compatible batch size scheduler library.
Author-email: George Stoica <george.stoica@info.uaic.ro>
Maintainer-email: George Stoica <george.stoica@info.uaic.ro>
License: BSD 3-Clause License
Project-URL: Repository, https://github.com/ancestor-mithril/bs-scheduler
Project-URL: Issues, https://github.com/ancestor-mithril/bs-scheduler/issues
Keywords: deep learning,pytorch,batch size scheduler,dynamic batch size
Classifier: Development Status :: 5 - Production/Stable
Classifier: Intended Audience :: Developers
Classifier: Intended Audience :: Science/Research
Classifier: Programming Language :: Python :: 3
Classifier: License :: OSI Approved :: BSD License
Classifier: Topic :: Scientific/Engineering :: Artificial Intelligence
Requires-Python: >=3.9
License-File: LICENSE
Requires-Dist: torch>=1.1.0
Provides-Extra: docs
Requires-Dist: mkdocs; extra == "docs"
Requires-Dist: mkdocstrings[python]; extra == "docs"
Requires-Dist: mkdocs-material; extra == "docs"
Provides-Extra: dev
Requires-Dist: matplotlib; extra == "dev"
Requires-Dist: pytest; extra == "dev"
Requires-Dist: flake8; extra == "dev"
Dynamic: license-file
